README.txt
setup.cfg
setup.py
bdt/__init__.py
bdt/dl8chan.py
bdt_8chan.egg-info/PKG-INFO
bdt_8chan.egg-info/SOURCES.txt
bdt_8chan.egg-info/dependency_links.txt
bdt_8chan.egg-info/entry_points.txt
bdt_8chan.egg-info/requires.txt
bdt_8chan.egg-info/top_level.txt