Metadata-Version: 1.1
Name: bdt-8chan
Version: 1.0.01105.5b1
Summary: 8Chan Thread Archiver - Downloads a thread; images, webms and all.
Home-page: http://github.com/xenmen/bdt_8chan
Author: Daniel Tadeuszow
Author-email: dtadeuszow@gmail.com
License: AGPL3+
Platform: UNKNOWN
Classifier: Development Status :: 5 - Production/Stable
Classifier: License :: OSI Approved :: GNU Affero General Public License v3 or later (AGPLv3+)
Classifier: Operating System :: POSIX
Classifier: Operating System :: Microsoft :: Windows
Classifier: Operating System :: MacOS :: MacOS X
Classifier: Programming Language :: Python :: 2.7
Classifier: Intended Audience :: Developers
Classifier: Intended Audience :: System Administrators
Classifier: Topic :: Internet :: WWW/HTTP
Classifier: Topic :: Text Processing :: Indexing
Classifier: Topic :: Text Processing :: Markup :: HTML
Classifier: Topic :: Utilities
